mavrykchain/_version.py
mavrykchain/keys.py
mavrykchain/mkmavrykchain.py
mavrykchain/parameters.yaml
mkmavrykchain-6.30.5.dist-info/METADATA
mkmavrykchain-6.30.5.dist-info/WHEEL
mkmavrykchain-6.30.5.dist-info/entry_points.txt
mkmavrykchain-6.30.5.dist-info/top_level.txt
mkmavrykchain-6.30.5.dist-info/RECORD
