Metadata-Version: 2.4
Name: mkmavrykchain
Version: 6.30.5
Summary: A utility to generate k8s configs for a Mavryk blockchain
Home-page: https://github.com/mavryk-network/mavryk-k8s
Author: MavrykDynamics
Classifier: Programming Language :: Python :: 3
Classifier: License :: OSI Approved :: MIT License
Classifier: Operating System :: OS Independent
Requires-Python: >=3.7
Requires-Dist: pyyaml
Provides-Extra: dev
Requires-Dist: pytest; extra == "dev"
Requires-Dist: autoflake; extra == "dev"
Requires-Dist: isort; extra == "dev"
Requires-Dist: black; extra == "dev"
Dynamic: author
Dynamic: classifier
Dynamic: description
Dynamic: description-content-type
Dynamic: home-page
Dynamic: provides-extra
Dynamic: requires-dist
Dynamic: requires-python
Dynamic: summary
